<animations>

	<!--Emotion Animations -->
	<emote>
		<id_string>annoyed</id_string>
		<image>annoyed.png</image>
		<frame_width>32</frame_width>
		<frame_height>32</frame_height>
		<delay>0.2</delay>
	</emote>
	
	<emote>
		<id_string>dotdotdot</id_string>
		<image>dotdotdot.png</image>
		<frame_width>32</frame_width>
		<frame_height>32</frame_height>
		<delay>0.5</delay>
	</emote>
	<emote>
		<id_string>exclamation</id_string>
		<image>exclamation.png</image>
		<frame_width>32</frame_width>
		<frame_height>32</frame_height>
		<delay>0.2</delay>
	</emote>
	<emote>
		<id_string>heart</id_string>
		<image>heart.png</image>
		<frame_width>32</frame_width>
		<frame_height>32</frame_height>
		<delay>0.2</delay>
	</emote>
	<emote>
		<id_string>lightbulb</id_string>
		<image>lightbulb.png</image>
		<frame_width>32</frame_width>
		<frame_height>32</frame_height>
		<delay>0.2</delay>
	</emote>
	<emote>
		<id_string>musicnote</id_string>
		<image>musicnote.png</image>
		<frame_width>32</frame_width>
		<frame_height>32</frame_height>
		<delay>0.2</delay>
	</emote>
	<emote>
		<id_string>questionmark</id_string>
		<image>questionmark.png</image>
		<frame_width>32</frame_width>
		<frame_height>32</frame_height>
		<delay>0.2</delay>
	</emote>
	<emote>
		<id_string>scribble</id_string>
		<image>scribble.png</image>
		<frame_width>32</frame_width>
		<frame_height>32</frame_height>
		<delay>0.2</delay>
	</emote>
	<emote>
		<id_string>sweatdrop</id_string>
		<image>sweatdrop.png</image>
		<frame_width>32</frame_width>
		<frame_height>32</frame_height>
		<delay>0.2</delay>
	</emote>
	<emote>
		<id_string>zzz</id_string>
		<image>zzz.png</image>
		<frame_width>32</frame_width>
		<frame_height>32</frame_height>
		<delay>0.2</delay>
	</emote>
	
	
	<!-- Effect Animations -->
	<effect>
		<id_string>fire_spell</id_string>
		<image>50x50_firespell.png</image>
		<frame_width>50</frame_width>
		<frame_height>50</frame_height>
		<delay>0.05</delay>
	</effect>

    <effect>
        <id_string>barrier_spell</id_string>

        <image>100x100_barrier.png</image>
        <frame_width>100</frame_width>
        <frame_height>100</frame_height>
        <delay>0.03</delay>
    </effect>
    <effect>
        <id_string>healing_spell</id_string>
        <image>100x100_healing.png</image>
        <frame_width>100</frame_width>
        <frame_height>100</frame_height>
        <delay>0.03</delay>
    </effect>
    <effect>
        <id_string>magic_cast</id_string>
        <image>100x100_magiccircle.png</image>
        <frame_width>100</frame_width>
        <frame_height>100</frame_height>
        <delay>0.03</delay>
    </effect>
    <effect>
        <id_string>light_spell</id_string>
        <image>100x100_lightspell.png</image>
        <frame_width>100</frame_width>
        <frame_height>100</frame_height>
        <delay>0.03</delay>
    </effect>
    <effect>
        <id_string>red_spell</id_string>
        <image>100x100_redspell.png</image>
        <frame_width>100</frame_width>
        <frame_height>100</frame_height>
        <delay>0.04</delay>
    </effect>
    <effect>
        <id_string>sealing_spell</id_string>
        <image>192x192_lightspell.png</image>
        <frame_width>192</frame_width>
        <frame_height>192</frame_height>
        <delay>0.05</delay>
    </effect>
    <effect>
        <id_string>asa_light_spell</id_string>
        <image>192x192_fivecolored_lights.png</image>
        <frame_width>192</frame_width>
        <frame_height>192</frame_height>
        <delay>0.03</delay>
    </effect>
	
</animations>
